setup.py
wxpay_sdk/WxPayAppPay.py
wxpay_sdk/WxPayJsApiPay.py
wxpay_sdk/WxPayNativePay.py
wxpay_sdk/__init__.py
wxpay_sdk/notify.py
wxpay_sdk.egg-info/PKG-INFO
wxpay_sdk.egg-info/SOURCES.txt
wxpay_sdk.egg-info/dependency_links.txt
wxpay_sdk.egg-info/requires.txt
wxpay_sdk.egg-info/top_level.txt
wxpay_sdk.egg-info/zip-safe
wxpay_sdk/core/WxPayApi.py
wxpay_sdk/core/WxPayConfig.py
wxpay_sdk/core/WxPayData.py
wxpay_sdk/core/WxPayException.py
wxpay_sdk/core/WxPayNotify.py
wxpay_sdk/core/__init__.py