Metadata-Version: 1.0
Name: wxpay-sdk
Version: 0.0.4
Summary: this is a package for weixin pay
Home-page: https://github.com/minkedong/wxpay_sdk
Author: minkedong
Author-email: minkedong89@126.com
License: Free
Keywords: wxpay_sdk weixin wechat wechatpay wechatsdk
Platform: UNKNOWN
